openergy/__init__.py
openergy/client.py
openergy/local.py
openergy/series_io.py
openergy/util.py
openergy/version.py
openergy/configurators/__init__.py
openergy/configurators/api.py
openergy/configurators/cleaner.py
openergy/configurators/importer.py
openergy/configurators/resources/multiclean_config_model.xlsx
openergy/outil/__init__.py
openergy/outil/async.py
openergy/outil/datetime.py
openergy/outil/exceptions.py
openergy/outil/json.py
openergy/outil/requests.py
openergy/outil/util.py
openergy/tests/__init__.py
openergy/tests/test_local_db.py
openergy-3.1.4.dist-info/DESCRIPTION.rst
openergy-3.1.4.dist-info/METADATA
openergy-3.1.4.dist-info/RECORD
openergy-3.1.4.dist-info/WHEEL
openergy-3.1.4.dist-info/metadata.json
openergy-3.1.4.dist-info/top_level.txt
