Metadata-Version: 2.0
Name: openergy
Version: 3.1.4
Summary: UNKNOWN
Home-page: https://github.com/openergy/openergy
Author: Geoffroy d'Estaintot
Author-email: geoffroy.destaintot@openergy.fr
License: UNKNOWN
Platform: UNKNOWN
Classifier: Programming Language :: Python
Classifier: Development Status :: 5 - Production/Stable
Classifier: Natural Language :: French
Classifier: Operating System :: POSIX :: Linux
Classifier: Programming Language :: Python :: 3.4
Requires-Dist: nose (<2.0.0,>=1.3.7)
Requires-Dist: openpyxl (<3.0.0,>=2.4.7)
Requires-Dist: pandas (>=0.20.1,<0.21.0)
Requires-Dist: python-slugify (>=1.2.1,<2.*)
Requires-Dist: requests (>=2.14.2,<3.0.0)
Requires-Dist: tables (<4.0,>=3.2.0)
